Workbook

Sheet BAU
A1: BAU Scenario | B1: Quantity | C1: Unit | D1: Source | E1: Comments
A2: Treated wastewater from Bengaluru
A3: Redirected for lake recharge | B3: =SUMIF(Sources!$H$3:$H$35,1,Sources!$F$3:$F$35) -> 564.69 | C3: MLD | D3: Ahmad and Singhal (2024), Annexure 3
A4: Total number of tanks supplied to | B4: 187 | C4: tanks | D4: Ahmad and Singhal (2024), pg 138 and pg 140 | E4: assuming tanks are lakes and that they have mentioned all the tanks in the report
A5: Per tank supply | B5: =B3/B4 -> 3.0197326 | C5: MLD per tank | D5: Calculated
A7: Devanahalli Demographics
A8: Total Population of Devanahalli town | B8: 38000 | C8: people | D8: Ahmad and Singhal (2024), pg 143
A9: Percentage of people in agricultural work | B9: =Sources!F75 -> 0.21381087 | C9: percent | D9: Primary census 2011 karnataka | E9: percentage from Bangalore rural district
A10: Number of people involved in agricultural work | B10: =$B$8*$B$9 -> 8124.8131 | C10: people | D10: Calculated
A11: Number of people not involved in agricultural work | B11: =B8-B10 -> 29875.187 | C11: people | D11: Calculated
A13: Devanahalli water pathway
A14: Total water demanded by Devanahalli town | B14: 2090000 | C14: Litres per day | D14: Ahmad and Singhal (2024), pg 143 | E14: using Devanahalli case study
A15: Number of tanks receiving water (Devanahalli) | B15: 9 | C15: tanks | D15: Ahmad and Singhal (2024), Table 31, pg 137
A16: Water supplied by revitalized well to town | B16: =Sources!A112 -> 159000 | C16: Litres per day | D16: Ahmad and Singhal (2024), pg 147 | E16: well near Sihineeru kere
A17: Percentage of water used for irrigation in agriculture | B17: 0.84 | C17: percent | D17: Ahmad and Singhal (2024), pg 143 (irrigate 84%) | E17: assuming Karnataka-wide value holds good here
A18: Percentage of water used for domestic use | B18: 0.08 | C18: percent | D18: Assumed | E18: assuming 8%
A19: Percentage of water used for drinking | B19: 0.08 | C19: percent | D19: Assumed | E19: assuming 8%
A20: Water from well used for irrigation in agriculture | B20: =$B$16*B17 -> 133560 | C20: Litres per day | D20: Calculated
A21: Water from well used for domestic use | B21: =$B$16*B18 -> 12720 | C21: Litres per day | D21: Calculated
A22: Water from well used for drinking | B22: =$B$16*B19 -> 12720 | C22: Litres per day | D22: Calculated
A24: Exposure to water
A25: Exposure to well water if involved in agricultural work | B25: =(B20/B10) + (B21/B8) + (B22/B8) -> 17.108006 | C25: Litres per day per person | D25: Calculated | E25: exposed to both irrigation water plus domestic and drinking water
A26: Exposure to well water if not involved in agricultural work | B26: =(B21/B8) + (B22/B8) -> 0.66947368 | C26: Litres per day per person | D26: Calculated | E26: exposed only to domestic and drinking water
A28: Chance of ingestion during irrigation | B28: 1e-05 | C28: percent | D28: Derived | E28: Ramesh et al. 2020 reports 0.1mL incidental ingestion per irrigation event. Assuming 10L of water is handled in such an event.
A29: Chance of ingestion during domestic use | B29: =B28*10 -> 0.0001 | C29: percent | D29: Assumed | E29: Assuming 10 times more likely to ingest during washing, bathing, etc., than during irrigation event.
A30: Chance of ingestion during drinking | B30: 1 | C30: percent | D30: Assumed
A32: Ingested volume of well water if involved in agricultural work | B32: =B28*(B20/B10) + B29*(B21/B8) + B30*(B22/B8) -> 0.3349347 | C32: Litres per day per person | D32: Calculated
A33: Ingested volume of well water if not involved in agricultural work | B33: =B29*(B21/B8) + B30*(B22/B8) -> 0.33477032 | C33: Litres per day per person | D33: Calculated
A35: Water Quality
A36: Concentration of E.coli | B36: =MIN(Sources!$B$59:$C$59) -> 9.12e-05 | C36: organisms per Litre | D36: George et al. 2015, Table 4 | E36: used the lower of both values, to simulate a better performing WTP
A37: Concentration of Rotavirus | B37: =MIN(Sources!$D$59:$E$59) -> 1.14e-08 | C37: organisms per Litre | D37: George et al. 2015, Table 4 | E37: used the lower of both values, to simulate a better performing WTP
A38: Concentration of Campylobacter | B38: =MIN(Sources!$F$59:$G$59) -> 0.0007524 | C38: organisms per Litre | D38: George et al. 2015, Table 4 | E38: used the lower of both values, to simulate a better performing WTP
A40: Exposure to Organisms
A41: Exposure to E.coli if involved in agricultural work | B41: =$B$32*B36 -> 3.0546045e-05 | C41: organisms per day per person | D41: Calculated | E41: Ingested volume x Concentration
A42: Exposure to Rotavirus if involved in agricultural work | B42: =$B$32*B37 -> 3.8182556e-09 | C42: organisms per day per person | D42: Calculated
A43: Exposure to Campylobacter if involved in agricultural work | B43: =$B$32*B38 -> 0.00025200487 | C43: organisms per day per person | D43: Calculated
A44: Exposure to E.coli if not involved in agricultural work | B44: =$B$33*B36 -> 3.0531053e-05 | C44: organisms per day per person | D44: Calculated
A45: Exposure to Rotavirus if not involved in agricultural work | B45: =$B$33*B37 -> 3.8163816e-09 | C45: organisms per day per person | D45: Calculated
A46: Exposure to Campylobacter if not involved in agricultural work | B46: =$B$33*B38 -> 0.00025188119 | C46: organisms per day per person | D46: Calculated
A48: Diarrheal Disease Risk
A49: Probability of infection by E.coli | B49: =Sources!B61 -> 0.001 | C49: dose-response parameter | D49: George et al. 2015, Table 4 | E49: r
A50: Probability of infection by Rotavirus | B50: =Sources!D61 -> 0.27 | C50: dose-response parameter | D50: George et al. 2015, Table 4
A51: Probability of infection by Campylobacter | B51: =Sources!F61 -> 0.018 | C51: dose-response parameter | D51: George et al. 2015, Table 4
A53: Probability of disease given infection (E.coli) | B53: =Sources!B64 -> 0.25 | C53: per case | D53: George et al. 2015, Table 4 | E53: P(disease|infection)
A54: Probability of disease given infection (Rotavirus) | B54: =Sources!D64 -> 0.5 | C54: per case | D54: George et al. 2015, Table 4
A55: Probability of disease given infection (Campylobacter) | B55: =Sources!F64 -> 0.3 | C55: per case | D55: George et al. 2015, Table 4
A57: - if involved in agricultural work -
A58: Risk of infection by E.coli | B58: =B41*$B$49 -> 3.0546045e-08 | C58: per person per day | D58: Calculated | E58: Pinf,d = E x r
A59: Risk of infection by Rotavirus | B59: =B42*$B$50 -> 1.030929e-09 | C59: per person per day | D59: Calculated
A60: Risk of infection by Campylobacter | B60: =B43*$B$51 -> 4.5360876e-06 | C60: per person per day | D60: Calculated
A62: Risk of infection by E.coli | B62: =1-((1-B58)^365) -> 1.1149244e-05 | C62: per person per year | D62: Calculated | E62: Pinf,y = 1-(1-Pinf,d)^365
A63: Risk of infection by Rotavirus | B63: =1-((1-B59)^365) -> 3.7628902e-07 | C63: per person per year | D63: Calculated
A64: Risk of infection by Campylobacter | B64: =1-((1-B60)^365) -> 0.0016543059 | C64: per person per year | D64: Calculated
A66: Risk of diarrheal disease by E.coli | B66: =B62*$B$53 -> 2.7873111e-06 | C66: per person per year | D66: Calculated | E66: Risk of infection x P(disease|infection)
A67: Risk of diarrheal disease by Rotavirus | B67: =B63*$B$54 -> 1.8814451e-07 | C67: per person per year | D67: Calculated
A68: Risk of diarrheal disease by Campylobacter | B68: =B64*$B$55 -> 0.00049629176 | C68: per person per year | D68: Calculated
A70: - if not involved in agricultural work -
A71: Risk of infection by E.coli | B71: =B44*$B$49 -> 3.0531053e-08 | C71: per person per day | D71: Calculated | E71: Pinf,d = E x r
A72: Risk of infection by Rotavirus | B72: =B45*$B$50 -> 1.030423e-09 | C72: per person per day | D72: Calculated
A73: Risk of infection by Campylobacter | B73: =B46*$B$51 -> 4.5338613e-06 | C73: per person per day | D73: Calculated
A75: Risk of infection by E.coli | B75: =1-((1-B71)^365) -> 1.1143772e-05 | C75: per person per year | D75: Calculated | E75: Pinf,y = 1-(1-Pinf,d)^365
A76: Risk of infection by Rotavirus | B76: =1-((1-B72)^365) -> 3.7610435e-07 | C76: per person per year | D76: Calculated
A77: Risk of infection by Campylobacter | B77: =1-((1-B73)^365) -> 0.0016534946 | C77: per person per year | D77: Calculated
A79: Risk of diarrheal disease by E.coli | B79: =B75*$B$53 -> 2.7859431e-06 | C79: per person per year | D79: Calculated | E79: Risk of infection x P(disease|infection)
A80: Risk of diarrheal disease by Rotavirus | B80: =B76*$B$54 -> 1.8805218e-07 | C80: per person per year | D80: Calculated
A81: Risk of diarrheal disease by Campylobacter | B81: =B77*$B$55 -> 0.00049604838 | C81: per person per year | D81: Calculated
A83: Exposed Population
A84: Estimated total population | B84: =ROUND(($B$8/$B$15)*B4,0) -> 789556 | C84: people | D84: Derived | E84: Devanahalli has 9 tanks for 38000 ppl; extrapolating this to (122 + 65) 187 tanks across Kolar, Chikbellapura, Blr urban and Blr rural districts
A85: Percentage of people in agricultural work | B85: =Sources!F72 -> 0.22481536 | C85: percent | D85: Primary census 2011 karnataka | E85: percentage from Karnataka-wide value
A86: Number of people involved in agricultural work | B86: =B84*B85 -> 177504.32 | C86: people | D86: Calculated
A87: Number of people not involved in agricultural work | B87: =B84-B86 -> 612051.68 | C87: people | D87: Calculated
A89: Disease Burden (DALY)
A90: Disease burden per case, DALY (E.coli) | B90: =Sources!G91 -> 0.45 | C90: DALY per case | D90: George et al. 2015, Table 3 | E90: Severity and duration of diarrhea are from studies done abroad
A91: Disease burden per case, DALY (Rotavirus) | B91: =Sources!G99 -> 0.44 | C91: DALY per case | D91: George et al. 2015, Table 3 | E91: Severity and duration of diarrhea are from studies done abroad
A92: Disease burden per case, DALY (Campylobacter) | B92: =Sources!G95 -> 0.0652 | C92: DALY per case | D92: George et al. 2015, Table 3 | E92: Severity and duration of diarrhea are from studies done abroad
A94: - if involved in agricultural work -
A95: Diarrheal disease burden from E.coli | B95: =B66*$B$86*B90 -> 0.22264189 | C95: DALY/year | D95: Calculated | E95: Risk of diarrheal disease x Disease burden per case x Exposed population
A96: Diarrheal disease burden from Rotavirus | B96: =B67*$B$86*B91 -> 0.014694443 | C96: DALY/year | D96: Calculated
A97: Diarrheal disease burden from Campylobacter | B97: =B68*$B$86*B92 -> 5.7437242 | C97: DALY/year | D97: Calculated
A99: - if not involved in agricultural work -
A100: Diarrheal disease burden from E.coli | B100: =B79*$B$87*B90 -> 0.76731352 | C100: DALY/year | D100: Calculated | E100: Risk of diarrheal disease x Disease burden per case x Exposed population
A101: Diarrheal disease burden from Rotavirus | B101: =B80*$B$87*B91 -> 0.050642967 | C101: DALY/year | D101: Calculated
A102: Diarrheal disease burden from Campylobacter | B102: =B81*$B$87*B92 -> 19.795193 | C102: DALY/year | D102: Calculated
A104: Total Disease burden in population | B104: =SUM(B95:B97,B100:B102) -> 26.59421 | C104: DALY/year | D104: Calculated | E104: Headline BAU figure: total annual DALYs from E.coli + Rotavirus + Campylobacter infection among the population drinking Sihineeru-Kere-recharged well water in Devanahalli, under current (BAU) conditions. Compare against WHO (2006) tolerable additional burden of 1e-6 DALY/person/year -- see row 42/43 for per-person exposed-population context.
A106: Value of disease burden
A107: Karnataka GSDP per capita in 2025-26 | B107: =Sources!D109 -> 477003 | C107: Rupees | D107: Karnataka Budget Analysis 2025-26 | E107: Human capital approach
A108: Value of DALYs (2025-26) | B108: =B104*B107/100000 -> 126.85518 | C108: Lakh Rupees | D108: Calculated

Sheet S2
A1: S2 Scenario | B1: Quantity | C1: Unit | D1: Source | E1: Comments
A2: Treated wastewater from Bengaluru
A3: Redirected for direct irrigation of farms | B3: =SUMIF(Sources!$H$3:$H$35,1,Sources!$F$3:$F$35) -> 564.69 | C3: MLD | D3: Ahmad and Singhal (2024), Annexure 3
A4: Total number of tanks supplied to | B4: 187 | C4: tanks | D4: Ahmad and Singhal (2024), pg 138 and pg 140 | E4: assuming tanks are lakes and that they have mentioned all the tanks in the report
A5: Per tank supply | B5: =B3/B4 -> 3.0197326 | C5: MLD per tank | D5: Calculated
A7: Devanahalli Demographics
A8: Total Population of Devanahalli town | B8: 38000 | C8: people | D8: Ahmad and Singhal (2024), pg 143
A9: Percentage of people in agricultural work | B9: =Sources!F75 -> 0.21381087 | C9: percent | D9: Primary census 2011 karnataka | E9: percentage from Bangalore rural district
A10: Number of people involved in agricultural work | B10: =$B$8*$B$9 -> 8124.8131 | C10: people | D10: Calculated
A11: Number of people not involved in agricultural work | B11: =B8-B10 -> 29875.187 | C11: people | D11: Calculated
A13: Devanahalli water pathway
A14: Total water demanded by Devanahalli town | B14: 2090000 | C14: Litres per day | D14: Ahmad and Singhal (2024), pg 143 | E14: using Devanahalli case study
A15: Number of tanks receiving water (Devanahalli) | B15: 9 | C15: tanks | D15: Ahmad and Singhal (2024), Table 31, pg 137
A16: Water supplied from TTP plant to town | B16: =Sources!A112 -> 159000 | C16: Litres per day | D16: Ahmad and Singhal (2024), pg 147 | E16: assuming TTP sends same amount of water as the well in the BAU
A17: Percentage of water used for irrigation in agriculture | B17: 1 | C17: percent | D17: Assumed | E17: assuming 100% because water not used for anything else
A18: Percentage of water used for domestic use | B18: 0 | C18: percent | D18: Assumed
A19: Percentage of water used for drinking | B19: 0 | C19: percent | D19: Assumed
A20: Water from well used for irrigation in agriculture | B20: =$B$16*B17 -> 159000 | C20: Litres per day | D20: Calculated
A21: Water from well used for domestic use | B21: =$B$16*B18 -> 0 | C21: Litres per day | D21: Calculated
A22: Water from well used for drinking | B22: =$B$16*B19 -> 0 | C22: Litres per day | D22: Calculated
A24: Exposure to water
A25: Exposure to well water if involved in agricultural work | B25: =(B20/B10) + (B21/B8) + (B22/B8) -> 19.569681 | C25: Litres per day per person | D25: Calculated | E25: exposed to both irrigation water plus domestic and drinking water
A26: Exposure to well water if not involved in agricultural work | B26: =(B21/B8) + (B22/B8) -> 0 | C26: Litres per day per person | D26: Calculated | E26: exposed only to domestic and drinking water
A28: Chance of ingestion during irrigation | B28: 1e-05 | C28: percent | D28: Derived | E28: Ramesh et al. 2020 reports 0.1mL incidental ingestion per irrigation event. Assuming 10L of water is handled in such an event.
A29: Chance of ingestion during domestic use | B29: =B28*10 -> 0.0001 | C29: percent | D29: Assumed | E29: Assuming 10 times more likely to ingest during washing, bathing, etc., than during irrigation event.
A30: Chance of ingestion during drinking | B30: 1 | C30: percent | D30: Assumed
A32: Ingested volume of well water if involved in agricultural work | B32: =B28*(B20/B10) + B29*(B21/B8) + B30*(B22/B8) -> 0.00019569681 | C32: Litres per day per person | D32: Calculated
A33: Ingested volume of well water if not involved in agricultural work | B33: =B29*(B21/B8) + B30*(B22/B8) -> 0 | C33: Litres per day per person | D33: Calculated
A35: Water Quality
A36: Concentration of E.coli | B36: =MIN(Sources!$B$58:$C$58) -> 9.12 | C36: organisms per Litre | D36: George et al. 2015, Table 4 | E36: used the better quality of raw water (Cauvery water) to simulate TTP
A37: Concentration of Rotavirus | B37: =MIN(Sources!$D$58:$E$58) -> 0.00114 | C37: organisms per Litre | D37: George et al. 2015, Table 4 | E37: used the better quality of raw water (Cauvery water) to simulate TTP
A38: Concentration of Campylobacter | B38: =MIN(Sources!$F$58:$G$58) -> 75.24 | C38: organisms per Litre | D38: George et al. 2015, Table 4 | E38: used the better quality of raw water (Cauvery water) to simulate TTP
A40: Exposure to Organisms
A41: Exposure to E.coli if involved in agricultural work | B41: =$B$32*B36 -> 0.0017847549 | C41: organisms per day per person | D41: Calculated | E41: Ingested volume x Concentration
A42: Exposure to Rotavirus if involved in agricultural work | B42: =$B$32*B37 -> 2.2309436e-07 | C42: organisms per day per person | D42: Calculated
A43: Exposure to Campylobacter if involved in agricultural work | B43: =$B$32*B38 -> 0.014724228 | C43: organisms per day per person | D43: Calculated
A44: Exposure to E.coli if not involved in agricultural work | B44: =$B$33*B36 -> 0 | C44: organisms per day per person | D44: Calculated
A45: Exposure to Rotavirus if not involved in agricultural work | B45: =$B$33*B37 -> 0 | C45: organisms per day per person | D45: Calculated
A46: Exposure to Campylobacter if not involved in agricultural work | B46: =$B$33*B38 -> 0 | C46: organisms per day per person | D46: Calculated
A48: Diarrheal Disease Risk
A49: Probability of infection by E.coli | B49: =Sources!B61 -> 0.001 | C49: dose-response parameter | D49: George et al. 2015, Table 4 | E49: r
A50: Probability of infection by Rotavirus | B50: =Sources!D61 -> 0.27 | C50: dose-response parameter | D50: George et al. 2015, Table 4
A51: Probability of infection by Campylobacter | B51: =Sources!F61 -> 0.018 | C51: dose-response parameter | D51: George et al. 2015, Table 4
A53: Probability of disease given infection (E.coli) | B53: =Sources!B64 -> 0.25 | C53: per case | D53: George et al. 2015, Table 4 | E53: P(disease|infection)
A54: Probability of disease given infection (Rotavirus) | B54: =Sources!D64 -> 0.5 | C54: per case | D54: George et al. 2015, Table 4
A55: Probability of disease given infection (Campylobacter) | B55: =Sources!F64 -> 0.3 | C55: per case | D55: George et al. 2015, Table 4
A57: - if involved in agricultural work -
A58: Risk of infection by E.coli | B58: =B41*$B$49 -> 1.7847549e-06 | C58: per person per day | D58: Calculated | E58: Pinf,d = E x r
A59: Risk of infection by Rotavirus | B59: =B42*$B$50 -> 6.0235478e-08 | C59: per person per day | D59: Calculated
A60: Risk of infection by Campylobacter | B60: =B43*$B$51 -> 0.0002650361 | C60: per person per day | D60: Calculated
A62: Risk of infection by E.coli | B62: =1-((1-B58)^365) -> 0.00065122398 | C62: per person per year | D62: Calculated | E62: Pinf,y = 1-(1-Pinf,d)^365
A63: Risk of infection by Rotavirus | B63: =1-((1-B59)^365) -> 2.1985708e-05 | C63: per person per year | D63: Calculated
A64: Risk of infection by Campylobacter | B64: =1-((1-B60)^365) -> 0.092217984 | C64: per person per year | D64: Calculated
A66: Risk of diarrheal disease by E.coli | B66: =B62*$B$53 -> 0.000162806 | C66: per person per year | D66: Calculated | E66: Risk of infection x P(disease|infection)
A67: Risk of diarrheal disease by Rotavirus | B67: =B63*$B$54 -> 1.0992854e-05 | C67: per person per year | D67: Calculated
A68: Risk of diarrheal disease by Campylobacter | B68: =B64*$B$55 -> 0.027665395 | C68: per person per year | D68: Calculated
A70: - if not involved in agricultural work -
A71: Risk of infection by E.coli | B71: =B44*$B$49 -> 0 | C71: per person per day | D71: Calculated | E71: Pinf,d = E x r
A72: Risk of infection by Rotavirus | B72: =B45*$B$50 -> 0 | C72: per person per day | D72: Calculated
A73: Risk of infection by Campylobacter | B73: =B46*$B$51 -> 0 | C73: per person per day | D73: Calculated
A75: Risk of infection by E.coli | B75: =1-((1-B71)^365) -> 0 | C75: per person per year | D75: Calculated | E75: Pinf,y = 1-(1-Pinf,d)^365
A76: Risk of infection by Rotavirus | B76: =1-((1-B72)^365) -> 0 | C76: per person per year | D76: Calculated
A77: Risk of infection by Campylobacter | B77: =1-((1-B73)^365) -> 0 | C77: per person per year | D77: Calculated
A79: Risk of diarrheal disease by E.coli | B79: =B75*$B$53 -> 0 | C79: per person per year | D79: Calculated | E79: Risk of infection x P(disease|infection)
A80: Risk of diarrheal disease by Rotavirus | B80: =B76*$B$54 -> 0 | C80: per person per year | D80: Calculated
A81: Risk of diarrheal disease by Campylobacter | B81: =B77*$B$55 -> 0 | C81: per person per year | D81: Calculated
A83: Exposed Population
A84: Estimated total population | B84: =ROUND(($B$8/$B$15)*B4,0) -> 789556 | C84: people | D84: Derived | E84: Devanahalli has 9 tanks for 38000 ppl; extrapolating this to (122 + 65) 187 tanks across Kolar, Chikbellapura, Blr urban and Blr rural districts
A85: Percentage of people in agricultural work | B85: =Sources!F72 -> 0.22481536 | C85: percent | D85: Primary census 2011 karnataka | E85: percentage from Karnataka-wide value
A86: Number of people involved in agricultural work | B86: =B84*B85 -> 177504.32 | C86: people | D86: Calculated
A87: Number of people not involved in agricultural work | B87: =B84-B86 -> 612051.68 | C87: people | D87: Calculated
A89: Disease Burden (DALY)
A90: Disease burden per case, DALY (E.coli) | B90: =Sources!G91 -> 0.45 | C90: DALY per case | D90: George et al. 2015, Table 3 | E90: Severity and duration of diarrhea are from studies done abroad
A91: Disease burden per case, DALY (Rotavirus) | B91: =Sources!G99 -> 0.44 | C91: DALY per case | D91: George et al. 2015, Table 3 | E91: Severity and duration of diarrhea are from studies done abroad
A92: Disease burden per case, DALY (Campylobacter) | B92: =Sources!G95 -> 0.0652 | C92: DALY per case | D92: George et al. 2015, Table 3 | E92: Severity and duration of diarrhea are from studies done abroad
A94: - if involved in agricultural work -
A95: Diarrheal disease burden from E.coli | B95: =B66*$B$86*B90 -> 13.004445 | C95: DALY/year | D95: Calculated | E95: Risk of diarrheal disease x Disease burden per case x Exposed population
A96: Diarrheal disease burden from Rotavirus | B96: =B67*$B$86*B91 -> 0.85856279 | C96: DALY/year | D96: Calculated
A97: Diarrheal disease burden from Campylobacter | B97: =B68*$B$86*B92 -> 320.1794 | C97: DALY/year | D97: Calculated
A99: - if not involved in agricultural work -
A100: Diarrheal disease burden from E.coli | B100: =B79*$B$87*B90 -> 0 | C100: DALY/year | D100: Calculated | E100: Risk of diarrheal disease x Disease burden per case x Exposed population
A101: Diarrheal disease burden from Rotavirus | B101: =B80*$B$87*B91 -> 0 | C101: DALY/year | D101: Calculated
A102: Diarrheal disease burden from Campylobacter | B102: =B81*$B$87*B92 -> 0 | C102: DALY/year | D102: Calculated
A104: Total Disease burden in population | B104: =SUM(B95:B97,B100:B102) -> 334.04241 | C104: DALY/year | D104: Calculated | E104: Headline BAU figure: total annual DALYs from E.coli + Rotavirus + Campylobacter infection among the population drinking Sihineeru-Kere-recharged well water in Devanahalli, under current (BAU) conditions. Compare against WHO (2006) tolerable additional burden of 1e-6 DALY/person/year -- see row 42/43 for per-person exposed-population context.
A106: Value of disease burden
A107: Karnataka GSDP per capita in 2025-26 | B107: =Sources!D109 -> 477003 | C107: Rupees | D107: Karnataka Budget Analysis 2025-26 | E107: Human capital approach
A108: Value of DALYs (2025-26) | B108: =B104*B107/100000 -> 1593.3923 | C108: Lakh Rupees | D108: Calculated

Sheet Sensitivity
A1: List of possible variants | B1: Comments | C1: Influence
A2: Total number of tanks the scheme supplies
A3: Total population of Devanahalli town
A4: % of Devanahalli population in agricultural work
A5: Number of tanks receiving water in Devanahalli
A6: Total water supplied from well/plant to town | B6: can vary quite a bit depending on town | C6: common to both
A7: % of water used for irrigation
A8: % of water used for domestic use
A9: % of water used for drinking
A10: Chance of ingestion during irrigation | B10: highly uncertain because of how I derived it | C10: common to both
A11: Chance of ingestion during domestic use | B11: highly uncertain because of how I derived it
A12: Chance of ingestion during drinking | B12: highly uncertain because of how I derived it
A13: E. coli concentration | B13: uncertain because secondary data from a different treatment plant / water body
A14: Rotavirus concentration | B14: uncertain because secondary data from a different treatment plant / water body
A15: Campylobacter concentration | B15: uncertain because secondary data from a different treatment plant / water body | C15: very high influence
A16: Dose-response parameter (r), per pathogen
A17: Probability of illness given infection, per pathogen
A18: % of wider population in agricultural work
A19: Disease burden per case (DALYs), per pathogen
A20: Karnataka GSDP per capita
A23: Total water supplied (common for both) | B23: BAU DALY | C23: S2 DALY | D23: Net DALY value | F23: Slope
A24: 159000 | B24: 126.85518 | C24: 1593.3923 | D24: 1466.5372 | F24: 0.0083
A25: 0 | B25: 0 | C25: 0 | D25: 0
A26: 2 | B26: 0.0015969354 | C26: 0.020984563 | D26: 0.019387628
A27: 1000 | B27: 0.79845993 | C27: 10.48923 | D27: 9.6907697
A28: 5000 | B28: 3.9922201 | C28: 52.385068 | D28: 48.392848
A29: 10000 | B29: 7.9842413 | C29: 104.61771 | D29: 96.633473
A30: 50000 | B30: 39.913246 | C30: 517.04662 | D30: 477.13337
A31: 100000 | B31: 79.806597 | C31: 1019.2592 | D31: 939.45261
A32: 500000 | B32: 398.23844 | C32: 4553.3121 | D32: 4155.0736
A34: Chance of ingestion of water during irrigation (common for both) | B34: BAU DALY | C34: S2 DALY | D34: Net DALY value | F34: Slope
A35: 1e-05 | B35: 126.85518 | C35: 1593.3923 | D35: 1466.5372 | F35: 100000000
A36: 5e-05 | B36: 126.96183 | C36: 6684.7677 | D36: 6557.8059
A37: 0.0001 | B37: 127.09515 | C37: 10934.373 | D37: 10807.278
A38: 5e-06 | B38: 126.84185 | C38: 815.11758 | D38: 688.27574
A39: 1e-06 | B39: 126.83118 | C39: 166.05682 | D39: 39.225638
A40: 7.6294e-07 | B40: 126.83055 | C40: 126.83041 | D40: -0.00013793153
A42: Campylobacter concentration (in BAU) | B42: BAU DALY | C42: S2 DALY | D42: Net DALY value | F42: Slope
A43: 0.0007524 | B43: 126.85518 | C43: 1593.3923 | D43: 1466.5372 | F43: -160084
A44: 0.003762 | B44: 612.13505 | C44: 1593.3923 | D44: 981.25728
A45: 0.007524 | B45: 1214.2467 | C45: 1593.3923 | D45: 379.14562
A46: 0.00989406 | B46: 1591.0335 | C46: 1593.3923 | D46: 2.3587833
A47: 0.0099089349 | B47: 1593.3922 | C47: 1593.3923 | D47: 0.00017821101
A49: Campylobacter concentration (in S2) | B49: BAU DALY | C49: S2 DALY | D49: Net DALY value | F49: Slope
A50: 75.24 | B50: 126.85518 | C50: 1593.3923 | D50: 1466.5372 | F50: 19.432
A51: 150.48 | B51: 126.85518 | C51: 2980.1665 | D51: 2853.3113
A52: 37.62 | B52: 126.85518 | C52: 848.17602 | D52: 721.32084
A53: 7.524 | B53: 126.85518 | C53: 225.56927 | D53: 98.71409
A54: 3.762 | B54: 126.85518 | C54: 146.04039 | D54: 19.185214
A55: 2.85912 | B55: 126.85518 | C55: 126.89631 | D55: 0.041132275
A56: 2.8571638 | B56: 126.85518 | C56: 126.85481 | D56: -0.00037063574
A61: Variant | B61: Min of range | C61: Max of range | D61: Value at which net DALY value turns negative | E61: Slope (Lakh Rs per unit change) | F61: times of "normal"
A62: Total water supplied | B62: =MIN(A24:A32) -> 0 | C62: =MAX(A24:A32) -> 500000 | D62: NA | E62: =F24 -> 0.0083 | F62: NA
A63: Chance of ingestion of water during irrigation | B63: =MIN(A35:A40) -> 7.6294e-07 | C63: =MAX(A35:A40) -> 0.0001 | D63: =A40 -> 7.6294e-07 | E63: =F35 -> 100000000 | F63: =D63/A35 -> 0.076294
A64: Campylobacter concentration (in BAU) | B64: =MIN(A43:A47) -> 0.0007524 | C64: =MAX(A43:A47) -> 0.0099089349 | D64: =A47 -> 0.0099089349 | E64: =F43 -> -160084 | F64: =D64/A43 -> 13.16977
A65: Campylobacter concentration (in S2) | B65: =MIN(A50:A56) -> 2.8571638 | C65: =MAX(A50:A56) -> 150.48 | D65: =A56 -> 2.8571638 | E65: =F50 -> 19.432 | F65: =D65/A50 -> 0.037974

Sheet Sources
A1: Annexure 3 of Ahmad and Singhal, 2024
A2: S. No. | B2: STP | C2: Location | D2: Total capacity utilized (MLD) | E2: Capacity utilized (MLD) | F2: Tread sewage reused (MLD) | G2: Used for | H2: Use_case_coded
A3: 1 | B3: Rajacanal | C3: Bengaluru | D3: 40 | E3: 32.68 | F3: 30.25 | G3: Irrigation and industrial | H3: 2 | J3: 1 | K3: Lake
A4: 2 | B4: Rajacanal | C4: Bengaluru | D4: 40 | E4: 40.51 | F4: 40.18 | G4: Irrigation and industrial | H4: 2 | J4: 2 | K4: Irrigation and industrial
A5: 3 | B5: Horamavu | C5: Bengaluru | D5: 20 | E5: 16.57 | F5: 14.96 | G5: Irrigation and industrial | H5: 2 | J5: 3 | K5: Others
A6: 4 | B6: Hebbal | C6: Bengaluru | D6: 100 | E6: 86.54 | F6: 84.5 | G6: Irrigation and industrial | H6: 2
A7: 5 | B7: K&C Valley | C7: Bengaluru | D7: 218 | E7: 153.66 | F7: 146.55 | G7: Lakes of Kolar | H7: 1
A8: 6 | B8: K&C Valley | C8: Bengaluru | D8: 30 | E8: 31.41 | F8: 30.27 | G8: Lakes of Kolar | H8: 1
A9: 7 | B9: Bellandur Amanikere | C9: Bengaluru | D9: 90 | E9: 88.2 | F9: 77.76 | G9: Lakes of Kolar | H9: 1
A10: 8 | B10: Jakkur | C10: Bengaluru | D10: 15 | E10: 17.18 | F10: 17.08 | G10: To KPTCL for power generation, remaining to Jakkuru lake | H10: 2
A11: 9 | B11: Sarakki | C11: Bengaluru | D11: 5 | E11: 4.77 | F11: 4.67 | G11: Proposal to recharge Sarakki lake | H11: 1
A12: 10 | B12: Lalbagh | C12: Bengaluru | D12: 1.5 | E12: 1.23 | F12: 1.17 | G12: Horticulture department | H12: 3
A13: 11 | B13: Cubbon Park | C13: Bengaluru | D13: 4 | E13: 2.5 | F13: 2.07 | G13: Horticulture | H13: 3
A14: 12 | B14: Yelhanka | C14: Bengaluru | D14: 10 | E14: 9.97 | F14: 1.76 | G14: Industrial | H14: 3
A15: 13 | B15: Yelemelle chetty | C15: Bengaluru | D15: 15 | E15: 13.63 | F15: 13.29 | G15: Lake | H15: 1
A16: 14 | B16: Chikkabanavar | C16: Bengaluru | D16: 5 | E16: 4.88 | F16: 4.59 | G16: Lake | H16: 1
A17: 15 | B17: Mailsandra | C17: Bengaluru | D17: 100 | E17: 80.03 | F17: 0.318 | G17: Horticulture | H17: 3
... A34: 32 | B34: Madiwala | C34: Bengaluru | D34: 4 | E34: 2.08 | F34: 1.99 | G34: Madiwala lake | H34: 1
A35: 33 | B35: V Valley | C35: Bengaluru | D35: 150 | E35: 142.46 | G35: SWD | H35: 3
A36: 34 | B36: Hassan | C36: Not Bengaluru | D36: 10 | E36: 10 | F36: 2 | G36: Agriculture
A37: 35 | B37: Belur | C37: Not Bengaluru | D37: 5 | E37: 2.4 | F37: 0.4 | G37: Agriculture
A38: 36 | B38: Belur | C38: Not Bengaluru | D38: 0.3 | E38: 0.3 | F38: 0.3 | G38: Agriculture
A39: 37 | B39: Bannuru | C39: Not Bengaluru | D39: 3.8 | E39: 1.7 | F39: 1.5 | G39: Agriculture
A40: 38 | B40: Bannuru | C40: Not Bengaluru | D40: 0.15 | E40: 0.06 | F40: 0.05 | G40: Agriculture
A41: 39 | B41: Arasikere | C41: Not Bengaluru | D41: 12 | E41: 6 | F41: 6 | G41: Agriculture
A42: 40 | B42: Channarayapatna | C42: Not Bengaluru | D42: 4.6 | E42: 4.6 | F42: 1 | G42: Agriculture
A43: 41 | B43: Holenarasipura | C43: Not Bengaluru | D43: 3 | E43: 3 | F43: 0.5 | G43: Agriculture
A44: 42 | B44: Birur | C44: Not Bengaluru | D44: 2.64 | E44: 0.3 | F44: 0.15 | G44: Agriculture
A45: 43 | B45: Muddebihal | C45: Not Bengaluru | D45: 5.24 | E45: 4 | F45: 4 | G45: Treated sewage is discharged into nala for agriculture purpose
A46: 44 | B46: Tumkur | C46: Not Bengaluru | D46: 6 | E46: 2.7 | F46: 2.3 | G46: Agriculture
A47: 45 | B47: Mangaluru | C47: Not Bengaluru | D47: 43.5 | E47: 27 | F47: 27 | G47: Industry
... A52: 50 | B52: Basavana Bagewadi | C52: Not Bengaluru | D52: 0.25 | E52: 0.2 | F52: 0.2 | G52: Agriculture
B53: Total | D53: =SUM(D3:D52) -> 1537.23 | E53: =SUM(E3:E52) -> 1296.17 | F53: =SUM(F3:F52) -> 883.652
A56: Table 4 George et al 2015
A57: Parameters | B57: Pathogenic E. coli - Melapura | C57: Pathogenic E. coli - Hongally | D57: Rotavirus - Melapura | E57: Rotavirus - Hongally | F57: Campylobacter - Melapura | G57: Campylobacter - Hongally
A58: Raw water quality (CR) | B58: 9.12 | C58: 18.24 | D58: 0.00114 | E58: 0.00228 | F58: 75.24 | G58: 150.48
A59: Drinking water quality (CD) | B59: 9.12e-05 | C59: 0.000182 | D59: 1.14e-08 | E59: 2.28e-08 | F59: 0.0007524 | G59: 0.0015048
A60: Exposure by drinking water (E) | B60: 9.35e-05 | C60: 0.000187 | D60: 1.17e-08 | E60: 2.34e-08 | F60: 0.000771 | G60: 0.001542
A61: Dose-response (r) | B61: 0.001 | C61: 0.001 | D61: 0.27 | E61: 0.27 | F61: 0.018 | G61: 0.018
A62: Risk of infection (Pinf,d) | B62: 9.35e-08 | C62: 1.87e-07 | D62: 3.15e-09 | E62: 6.31e-09 | F62: 1.39e-05 | G62: 2.78e-05
A63: Risk of infection (Pinf,y) | B63: 3.41e-05 | C63: 6.82e-05 | D63: 1.15e-06 | E63: 2.3e-06 | F63: 0.00507 | G63: 0.0101
A64: Risk of diarrheal illness given infection (Pill/inf) | B64: 0.25 | C64: 0.25 | D64: 0.5 | E64: 0.5 | F64: 0.3 | G64: 0.3
A65: Risk of diarrheal disease (Pill) | B65: 8.53e-06 | C65: 1.71e-05 | D65: 5.76e-07 | E65: 1.15e-06 | F65: 4.16e-06 | G65: 8.33e-06
A66: Disease burden (db) | B66: 0.45 | C66: 0.45 | D66: 0.44 | E66: 0.44 | F66: 0.65 | G66: 0.65
A67: Susceptible fraction (fs) | B67: 0.18 | C67: 0.48 | D67: 0.18 | E67: 0.48 | F67: 0.18 | G67: 0.48
A68: Disease burden (db)/health outcome target (HT) | B68: 6.91e-07 | C68: 3.6e-06 | D68: 4.56e-08 | E68: 2.43e-07 | F68: 4.87e-07 | G68: 2.6e-06
A70: Primary census 2011 karnataka
A71: District | B71: WPR % (pg 58) | C71: Cultivators % of workers (pg 68) | D71: Agri. labourers % of workers (pg 71) | E71: Field workers % of workers (sum) | F71: Field workers % of total population
A72: Karnataka (state) | B72: 0.4562 | C72: 0.2361 | D72: 0.2567 | E72: =Table3[[#This Row],[Cultivators % of workers (pg 68)]]+Table3[[#This Row],[Agri. labourers % of workers (pg 71)]] -> 0.4928 | F72: =Table3[[#This Row],[Field workers % of workers (sum)]]*Table3[[#This Row],[WPR % (pg 58)]] -> 0.22481536
A73: Kolar | B73: 0.4672 | C73: 0.255 | D73: 0.2803 | E73: =Table3[[#This Row],[Cultivators % of workers (pg 68)]]+Table3[[#This Row],[Agri. labourers % of workers (pg 71)]] -> 0.5353 | F73: =Table3[[#This Row],[Field workers % of workers (sum)]]*Table3[[#This Row],[WPR % (pg 58)]] -> 0.25009216
A74: Chikkaballapura | B74: 0.5097 | C74: 0.3317 | D74: 0.3235 | E74: =Table3[[#This Row],[Cultivators % of workers (pg 68)]]+Table3[[#This Row],[Agri. labourers % of workers (pg 71)]] -> 0.6552 | F74: =Table3[[#This Row],[Field workers % of workers (sum)]]*Table3[[#This Row],[WPR % (pg 58)]] -> 0.33395544
A75: Bangalore Rural | B75: 0.4641 | C75: 0.2778 | D75: 0.1829 | E75: =Table3[[#This Row],[Cultivators % of workers (pg 68)]]+Table3[[#This Row],[Agri. labourers % of workers (pg 71)]] -> 0.4607 | F75: =Table3[[#This Row],[Field workers % of workers (sum)]]*Table3[[#This Row],[WPR % (pg 58)]] -> 0.21381087
A77: Table 3 of Ramesh et al. 2020
A78: Reuse option | B78: Exposed population | C78: Exposure route | D78: Vi (ingested volume per event) | E78: Distribution | F78: f (events/year) | G78: Reference
A79: Crop irrigation | B79: Field workers | C79: Accidental ingestion while performing farm activities (hose-pipe watering, aerosol/droplet splash), no protective gear | D79: 0,1–0,2 mL/Event | E79: Uniform | F79: 60–90 Event/yr | G79: Busgang et al.
A80: Crop irrigation | B80: Children | C80: Accidental/incidental ingestion while playing or working in the fields during irrigation | D80: 0,1–1 mL/Event | E80: Uniform | F80: 30–45 Event/yr | G80: This study (survey)
A81: Garden irrigation | B81: Field workers | C81: Accidental ingestion while performing garden activities (hose-pipe watering, aerosol/droplet splash), no protective gear | D81: 0,05–0,1 mL/Event | E81: Uniform | F81: 180–270 Event/yr | G81: Chhipi-Shrestha et al.
A82: Garden irrigation | B82: Children | C82: Accidental/incidental ingestion while playing in the garden during irrigation (children present the whole time) | D82: 0,09–0,11 mL/Event | E82: Uniform | F82: 52–104 Event/yr | G82: Chhipi-Shrestha et al.
A83: Toilet flush (occupational) | B83: Workers (adults) | C83: Aerosol ingestion during flushing | D83: 0,009–0,011 mL/Event | E83: Uniform | F83: 626–1.248 Event/yr | G83: Chhipi-Shrestha et al.
A84: Industrial reuse (occupational) | B84: Workers | C84: Accidental ingestion of aerosols while cleaning equipment/machines, no masks or gloves | D84: 0,09–0,11 mL/Event | E84: Uniform | F84: 2–12 Event/yr | G84: Chhipi-Shrestha et al.
A86: Table 3 of George et al. 2015
A87: Pathogen | B87: Outcome | C87: Severity | D87: Duration (days) | E87: Duration (years) | F87: Disease burden formula shown | G87: DALY per case (row)
A88: E. coli O157:H7 | B88: Watery diarrhea (53%) | C88: 0.067 | D88: 3.4 | E88: 0.009 | F88: 1.000 × 53% × 0,067 × 0,009 | G88: 0.3
A89: E. coli O157:H7 | B89: Bloody diarrhea (47%) | C89: 0.39 | D89: 5.6 | E89: 0.015 | F89: 1.000 × 47% × 0,39 × 0,015 | G89: 2.8
A90: E. coli O157:H7 | B90: Death from diarrhea | C90: 1 | D90: 64 years | E90: — | F90: 1.000 × 0,7% × 64 | G90: 448
A91: E. coli O157:H7 | B91: Total diarrhea | C91: — | D91: — | E91: — | F91: — | G91: 0.45
A92: Campylobacter | B92: Gastroenteritis, population (94%) | C92: 0.067 | D92: 3.48 | E92: 0,009 (see note) | F92: 0,94 × 0,067 × 0,009 | G92: 0.0006
A93: Campylobacter | B93: Gastroenteritis, GP visit (6%) | C93: 0.39 | D93: 9.72 | E93: 0.026 | F93: 0,06 × 0,39 × 0,026 | G93: 0.00062
A94: Campylobacter | B94: Death from gastroenteritis (0,1%) | C94: 1 | D94: 64 years | E94: — | F94: 0,001 × 1 × 64 | G94: 0.064
A95: Campylobacter | B95: Total | C95: — | D95: — | E95: — | F95: — | G95: 0.0652
A96: Rotavirus | B96: Mild diarrhea (85,6%) | C96: 0.1 | D96: 7 | E96: 0.02 | F96: 1 × 85,6% × 0,10 × 0,02 | G96: 0.002
A97: Rotavirus | B97: Severe diarrhea (14,4%) | C97: 0.23 | D97: 7 | E97: 0.02 | F97: 1 × 14,4% × 0,23 × 0,02 | G97: 0.0007
A98: Rotavirus | B98: Death | C98: 1 | D98: 64 years | E98: — | F98: 1 × 0,7% × 64 | G98: 0.448
A99: Rotavirus | B99: Total | C99: — | D99: — | E99: — | F99: — | G99: 0.44
A101: Labour commission notification 22nd May 2026: Minimum wages Karnataka | D101: https://karmikaspandana.karnataka.gov.in/47/minimum-wages-final-notification/en
A102: Skill category | B102: Zone 1 - Per day | C102: Zone 1 - Per month | D102: Zone 2 - Per day | E102: Zone 2 - Per month | F102: Zone 3 - Per day | G102: Zone 3 - Per month
A103: Highly Skilled | B103: 1196.69 | C103: 31114.02 | D103: 1087.9 | E103: 28285.47 | F103: 989 | G103: 25714.07
A104: Skilled | B104: 1087.9 | C104: 28285.47 | D104: 989 | E104: 25714.07 | F104: 899.09 | G104: 23376.43
A105: Semi-skilled | B105: 989 | C105: 25714.07 | D105: 899.09 | E105: 23376.43 | F105: 817.35 | G105: 21251.3
A106: Unskilled | B106: 899.09 | C106: 23376.43 | D106: 817.35 | E106: 21251.3 | F106: 743.05 | G106: 19319.36
A108: Karnataka Budget Analysis by PRS 2026-27 | C108: https://prsindia.org/budgets/states/karnataka-budget-analysis-2026-27
A109: Per capita GSDP: In 2025-26, Karnataka’s per capita GSDP (at current prices) is estimated to be Rs 4,77,003 | D109: 477003
A111: Total water supplied from well/ treatment plant based on Ahmad and Singhal 2024
A112: 159000 | B112: Litres per day
